greenswitch/__init__.py
greenswitch/esl.py
greenswitch-0.0.14.dist-info/LICENSE
greenswitch-0.0.14.dist-info/METADATA
greenswitch-0.0.14.dist-info/WHEEL
greenswitch-0.0.14.dist-info/pbr.json
greenswitch-0.0.14.dist-info/top_level.txt
greenswitch-0.0.14.dist-info/RECORD
