Metadata-Version: 2.1
Name: greenswitch
Version: 0.0.14
Summary: Battle proven FreeSWITCH Event Socket Protocol client implementation with Gevent.
Home-page: https://github.com/evoluxbr/greenswitch
Author: Ítalo Rossi
Author-email: italorossib@gmail.com
License: MIT
Platform: UNKNOWN
Classifier: Development Status :: 5 - Production/Stable
Classifier: Intended Audience :: Developers
Classifier: Programming Language :: Python
Classifier: License :: OSI Approved :: MIT License
Classifier: Programming Language :: Python :: 2.7
Classifier: Programming Language :: Python :: 3
Classifier: Programming Language :: Python :: 3.5
Classifier: Programming Language :: Python :: 3.6
Classifier: Programming Language :: Python :: 3.7
Classifier: Programming Language :: Python :: 3.8
Classifier: Programming Language :: Python :: 3.9
Classifier: Programming Language :: Python :: 3.10
Requires-Dist: gevent
Requires-Dist: six
